puffcoble/__init__.py
puffcoble/puffcoble.py
puffcoble/puffco/constants.py
puffcoble/utils/codec.py
puffcoble/utils/product_info.py
puffcoble/utils/rgbtApi2.py
puffcoble/utils/utils.py
puffcoble-0.1.1.dist-info/licenses/LICENSE
puffcoble-0.1.1.dist-info/METADATA
puffcoble-0.1.1.dist-info/WHEEL
puffcoble-0.1.1.dist-info/top_level.txt
puffcoble-0.1.1.dist-info/RECORD
