Metadata-Version: 2.4
Name: puffcoble
Version: 0.1.1
Summary: Python BLE SDK for Puffco Peak Pro devices
Author-email: Fr0st3h <owner@hexogen.app>
License-Expression: MIT
Classifier: Programming Language :: Python :: 3
Classifier: Operating System :: OS Independent
Requires-Python: >=3.10
License-File: LICENSE
Requires-Dist: bleak==0.22.3
Requires-Dist: bleak-winrt==1.2.0
Requires-Dist: cbor2==5.7.1
Requires-Dist: tamga==1.4.0
Requires-Dist: typing-extensions==4.15.0
Dynamic: license-file
